README.rst
setup.py
oauth2/__init__.py
oauth2/client_authenticator.py
oauth2/compatibility.py
oauth2/datatype.py
oauth2/error.py
oauth2/grant.py
oauth2/tokengenerator.py
oauth2/web.py
oauth2/store/__init__.py
oauth2/store/memcache.py
oauth2/store/memory.py
oauth2/store/mongodb.py
oauth2/test/__init__.py
oauth2/test/test_client_authenticator.py
oauth2/test/test_datatype.py
oauth2/test/test_grant.py
oauth2/test/test_oauth2.py
oauth2/test/test_tokengenerator.py
oauth2/test/test_web.py
python_oauth2.egg-info/PKG-INFO
python_oauth2.egg-info/SOURCES.txt
python_oauth2.egg-info/dependency_links.txt
python_oauth2.egg-info/top_level.txt