Metadata-Version: 1.1
Name: python-oauth2
Version: 0.6.0
Summary: OAuth 2.0 provider for python
Home-page: https://github.com/wndhydrnt/python-oauth2
Author: Markus Meyer
Author-email: hydrantanderwand@gmail.com
License: UNKNOWN
Platform: UNKNOWN
Classifier: Development Status :: 4 - Beta
Classifier: License :: OSI Approved :: MIT License
Classifier: Programming Language :: Python :: 2
Classifier: Programming Language :: Python :: 2.6
Classifier: Programming Language :: Python :: 2.7
Classifier: Programming Language :: Python :: 3
Classifier: Programming Language :: Python :: 3.2
Classifier: Programming Language :: Python :: 3.3
